lonhand/__init__.py
lonhand/device.py
lonhand-0.4.dist-info/LICENSE
lonhand-0.4.dist-info/METADATA
lonhand-0.4.dist-info/WHEEL
lonhand-0.4.dist-info/top_level.txt
lonhand-0.4.dist-info/RECORD
