Metadata-Version: 2.1
Name: lonhand
Version: 0.4
Summary: LonHand client library
Home-page: https://github.com/rp3tya/LonHand
Author: rp3tya
Author-email: rpetya@hotmail.com
License: UNKNOWN
Keywords: lonhand relay
Platform: UNKNOWN
Classifier: Programming Language :: Python :: 3
Classifier: License :: OSI Approved :: MIT License
Classifier: Operating System :: OS Independent
